nl2cmd/__init__.py
nl2cmd/cli.py
nl2cmd/command_mapper.py
nl2cmd/infer.py
nl2cmd/intent_classifier.py
nl2cmd/os_detect.py
nl2cmd/rule_engine.py
nl2cmd/safety.py
nl2cmd_cli-0.2.1.dist-info/METADATA
nl2cmd_cli-0.2.1.dist-info/WHEEL
nl2cmd_cli-0.2.1.dist-info/entry_points.txt
nl2cmd_cli-0.2.1.dist-info/top_level.txt
nl2cmd_cli-0.2.1.dist-info/RECORD
