Metadata-Version: 2.4
Name: nl2cmd-cli
Version: 0.2.1
Summary: Natural Language to Terminal Command Translator
Author: Nagashree N S, Riya Kumari
Requires-Python: >=3.9
Requires-Dist: sentencepiece
Requires-Dist: numpy
Provides-Extra: ml
Requires-Dist: torch; extra == "ml"
Requires-Dist: transformers; extra == "ml"
Requires-Dist: sentence-transformers>=2.2.0; extra == "ml"
Requires-Dist: scikit-learn; extra == "ml"
